unwrappy/__init__.py
unwrappy/exceptions.py
unwrappy/option.py
unwrappy/py.typed
unwrappy/result.py
unwrappy/serde.py
unwrappy-0.1.0.dist-info/WHEEL
unwrappy-0.1.0.dist-info/METADATA
unwrappy-0.1.0.dist-info/RECORD
