Metadata-Version: 2.3
Name: unwrappy
Version: 0.1.0
Summary: Yet another Rust-inspired Result and Option ergonomics brought to Python, enabling safe, expressive error handling with errors as values.
Author: Leonardo Diegues
Author-email: Leonardo Diegues <leo@diegues.dev>
Classifier: Development Status :: 4 - Beta
Classifier: Intended Audience :: Developers
Classifier: License :: OSI Approved :: MIT License
Classifier: Operating System :: OS Independent
Classifier: Programming Language :: Python :: 3
Classifier: Programming Language :: Python :: 3.10
Classifier: Programming Language :: Python :: 3.11
Classifier: Programming Language :: Python :: 3.12
Classifier: Programming Language :: Python :: 3.13
Classifier: Programming Language :: Python :: 3.14
Classifier: Programming Language :: Python :: 3 :: Only
Classifier: Topic :: Software Development :: Libraries
Classifier: Topic :: Software Development :: Libraries :: Python Modules
Classifier: Typing :: Typed
Requires-Python: >=3.10, <4.0
Project-URL: Repository, https://github.com/leodiegues/unwrappy
Project-URL: Documentation, https://github.com/leodiegues/unwrappy#readme
Project-URL: Changelog, https://github.com/leodiegues/unwrappy/releases
